knackhq/__init__.py
knackhq/exceptions.py
knackhq/knackhq.py
knackhq-0.3.0.dist-info/LICENSE
knackhq-0.3.0.dist-info/WHEEL
knackhq-0.3.0.dist-info/METADATA
knackhq-0.3.0.dist-info/RECORD
